LICENSE
README.md
setup.py
parseq_XAS/XAS_fits.py
parseq_XAS/XAS_nodes.py
parseq_XAS/XAS_pipeline.py
parseq_XAS/XAS_start.py
parseq_XAS/XAS_tests.py
parseq_XAS/XAS_transforms.py
parseq_XAS/XAS_widgets.py
parseq_XAS/__init__.py
parseq_XAS/version.py
parseq_XAS.egg-info/PKG-INFO
parseq_XAS.egg-info/SOURCES.txt
parseq_XAS.egg-info/dependency_links.txt
parseq_XAS.egg-info/not-zip-safe
parseq_XAS.egg-info/requires.txt
parseq_XAS.egg-info/top_level.txt
parseq_XAS/data/Cu2O_lnt1.fio
parseq_XAS/data/Cu2O_lnt2.fio
parseq_XAS/data/CuO_lnt.fio
parseq_XAS/data/Cu_lnt1.fio
parseq_XAS/data/Cu_lnt2.fio
parseq_XAS/data/Cu_rt1.fio
parseq_XAS/data/Cu_rt2.fio
parseq_XAS/data/cu-ref-mix.res
parseq_XAS/data/CeRu2/CE0074.DAT
parseq_XAS/data/CeRu2/RU0074.DAT
parseq_XAS/data/CeRu2/feff/CeRu2/feff0001.dat
parseq_XAS/data/CeRu2/feff/CeRu2/feff0002.dat
parseq_XAS/data/CeRu2/feff/CeRu2/feff0003.dat
parseq_XAS/data/CeRu2/feff/CeRu2/feff0004.dat
parseq_XAS/data/CeRu2/feff/CeRu2/feff0005.dat
parseq_XAS/data/CeRu2/feff/CeRu2/feff0006.dat
parseq_XAS/data/CeRu2/feff/CeRu2/feff0007.dat
parseq_XAS/data/CeRu2/feff/CeRu2/feff0008.dat
parseq_XAS/data/CeRu2/feff/CeRu2/feff0009.dat
parseq_XAS/data/CeRu2/feff/CeRu2/feff0010.dat
parseq_XAS/data/CeRu2/feff/CeRu2/feff0011.dat
parseq_XAS/data/CeRu2/feff/CeRu2/feff0012.dat
parseq_XAS/data/CeRu2/feff/CeRu2/feff0013.dat
parseq_XAS/data/CeRu2/feff/CeRu2/feff0014.dat
parseq_XAS/data/CeRu2/feff/CeRu2/feff0015.dat
parseq_XAS/data/CeRu2/feff/CeRu2/files.dat
parseq_XAS/data/CeRu2/feff/Ru_CeRu2/feff0001.dat
parseq_XAS/data/CeRu2/feff/Ru_CeRu2/feff0002.dat
parseq_XAS/data/CeRu2/feff/Ru_CeRu2/feff0003.dat
parseq_XAS/data/CeRu2/feff/Ru_CeRu2/feff0004.dat
parseq_XAS/data/CeRu2/feff/Ru_CeRu2/feff0005.dat
parseq_XAS/data/CeRu2/feff/Ru_CeRu2/feff0006.dat
parseq_XAS/data/CeRu2/feff/Ru_CeRu2/feff0007.dat
parseq_XAS/data/CeRu2/feff/Ru_CeRu2/feff0008.dat
parseq_XAS/data/CeRu2/feff/Ru_CeRu2/feff0009.dat
parseq_XAS/data/CeRu2/feff/Ru_CeRu2/feff0010.dat
parseq_XAS/data/CeRu2/feff/Ru_CeRu2/feff0011.dat
parseq_XAS/data/CeRu2/feff/Ru_CeRu2/feff0012.dat
parseq_XAS/data/CeRu2/feff/Ru_CeRu2/feff0013.dat
parseq_XAS/data/CeRu2/feff/Ru_CeRu2/feff0014.dat
